face/__init__.py
face/command.py
face/errors.py
face/helpers.py
face/middleware.py
face/parser.py
face/sinter.py
face/testing.py
face/utils.py
face/test/_search_cmd_a.flags
face/test/test_basic.py
face/test/test_calc_cmd.py
face/test/test_help.py
face/test/test_mw.py
face/test/test_search_cmd.py
face/test/test_vcs_cmd.py
face-22.0.0.dist-info/LICENSE
face-22.0.0.dist-info/METADATA
face-22.0.0.dist-info/WHEEL
face-22.0.0.dist-info/top_level.txt
face-22.0.0.dist-info/RECORD
